LICENSE.txt
MANIFEST.in
README.md
VERSION
pyproject.toml
setup.cfg
setup.py
nordigen/__init__.py
nordigen/client.py
nordigen_python.egg-info/PKG-INFO
nordigen_python.egg-info/SOURCES.txt
nordigen_python.egg-info/dependency_links.txt
nordigen_python.egg-info/not-zip-safe
nordigen_python.egg-info/requires.txt
nordigen_python.egg-info/top_level.txt