Metadata-Version: 2.1
Name: nordigen-python
Version: 0.1.2
Summary: Clinet lib for integration with Nordigen banking API's
Home-page: https://github.com/dogmatic69/nordigen-python
Author: Carl Sutton (dogmatic69)
Author-email: dogmatic69@gmail.com
License: MIT
Keywords: nordigen,banking,PSD2
Platform: UNKNOWN
Classifier: Development Status :: 3 - Alpha
Classifier: Programming Language :: Python :: 3.8
Classifier: License :: OSI Approved :: MIT License
Classifier: Operating System :: OS Independent
Classifier: Intended Audience :: Developers
Requires-Python: >=3.6
Provides-Extra: production
Provides-Extra: test
Provides-Extra: lint
Provides-Extra: docs
Provides-Extra: dev
Provides-Extra: deploy
